[
  {
    "category": "Real Estate & Property",
    "title": "Property appraisals and valuations",
    "volume": "Small",
    "retention": "5-10 years (financing/tax)",
    "dataVerified": "Appraiser name, property owner, address, valuation details",
    "dataVisibleAfterVerification": "Shows the issuer domain and the responder text (e.g., \"Valid ID\" or \"Denied\").",
    "rationale": "Domain binding verifies certified appraiser. Formal reports suitable for OCR. Prevents inflated valuations. Financing and tax documentation."
  }
]
